{
    "listings": {
        "boi": {
            "Boilers": {
                "no of listings": [],
                "title": [
                    "Free boilers for sale Goverment Scheme"
                ],
                "price": "0",
                "category": "boi",
                "description": "f your property qualifies for a grant, you can get a FREE NEW BOILER!\n\nECO4 Funding is available if you are :\n\n\u2705 Homeowner\n\u2705 Receiving Benefits \n\u2705 Boiler is 15 years old ( non - condensing boiler )\n\u2705 Energy Rating is D and lower",
                "path": "D:\\Personal\\Realcode\\Facebook-listing-app\\boilers",
                "change_location": "2",
                "id": "631860527729855",
                "id1": ""
            }
        },
        "Mattresses": {
            "Matresses": {
                "no of listings": [
                    11,
                    12,
                    13,
                    14,
                    15
                ],
                "title": [
                    "Brand New Mattresses \u2013 Limited Stock, Act Fast!",
                    "\ud83d\udd25 Huge Mattress Sale \u2013 Don\u2019t Miss Out!",
                    "Sleep Like Royalty \u2013 Premium Quality Mattresses!",
                    "Luxury Comfort at Affordable Prices \u2013 Brand New Mattresses!",
                    "Fast & Free UK Delivery \u2013 Shop Mattresses Now!",
                    "We Deliver to Your Door \u2013 New Mattresses Available Today!"
                ],
                "price": "70",
                "category": "Mattresses",
                "description": "\ud83d\udecf\ufe0f BRAND NEW MATTRESSES FOR SALE ALL OVER THE UK! \ud83d\udecd\ufe0f\nLooking for top-quality sleep without breaking the bank? You\u2019re in the right place!\nWe\u2019ve got a wide range of brand new mattresses to suit every comfort level and budget \ud83d\udcb7\n\n\u2728 Available Mattress Types:\n\n\ud83d\udecc PILLOW TOP POCKET MEMORY \u2013 12 inch luxury!\n\n\ud83c\udf00 POCKET 2000 \u2013 Superior individual spring support\n\n\ud83d\udd04 POCKET 1000 \u2013 Balanced comfort and support\n\n\ud83e\udde0 MEMORY FOAM \u2013 Contours perfectly to your body\n\n\ud83e\uddb4 ORTHOPAEDIC FIRM \u2013 Ideal for back support\n\n\ud83c\udf19 MEMORY FOAM SPRING \u2013 Best of both worlds!\n\n\ud83d\udcba STANDARD SPRING MATTRESS \u2013 Reliable and affordable\n\n\ud83c\udfaf Why Buy From Us? \u2714\ufe0f Brand New & Sealed\n\u2714\ufe0f All Sizes Available (Single, Double, King, Super King)\n\u2714\ufe0f Fast & FREE UK Delivery \ud83d\ude9a\n\u2714\ufe0f Great Prices \u2013 Message for the best deal!\n\u2714\ufe0f Always Available \u2013 Happy to Chat \ud83d\ude0a\n\n\ud83d\udcac Send us a message anytime for prices, info, or help choosing the right mattress \u2013 we're always here and happy to help!\n\n\ud83d\udce6 Stock moves fast \u2013 grab yours today and sleep better tonight!",
                "path": "D:\\Personal\\Realcode\\Facebook work\\Facebook listing\\furniture\\mattresses",
                "change_location": "2",
                "id": "663292461269908",
                "id1": ""
            }
        }
    }
}